gcxmlib.cpython-39-x86_64-linux-gnu.so
gcxmlib-0.1.dist-info/LICENSE
gcxmlib-0.1.dist-info/METADATA
gcxmlib-0.1.dist-info/WHEEL
gcxmlib-0.1.dist-info/top_level.txt
gcxmlib-0.1.dist-info/RECORD
