Metadata-Version: 2.1
Name: gcxmlib
Version: 0.1
Summary: GCXMlib: a library for x-matching with great circles
Home-page: https://bitbucket.org/ryou_ohsawa/gcxmlib/src/master/
Author: Ryou Ohsawa
Author-email: ohsawa@ioa.s.u-tokyo.ac.jp
Maintainer: Ryou Ohsawa
Maintainer-email: ohsawa@ioa.s.u-tokyo.ac.jp
License: MIT
Platform: UNKNOWN
Classifier: Development Status :: 3 - Alpha
Classifier: Environment :: Console
Classifier: Intended Audience :: Science/Research
Classifier: License :: OSI Approved :: MIT License
Classifier: Operating System :: POSIX :: Linux
Classifier: Programming Language :: Python :: 3
Classifier: Programming Language :: Python :: 3.7
Classifier: Programming Language :: Python :: Implementation :: CPython
Classifier: Topic :: Scientific/Engineering :: Astronomy
License-File: LICENSE
Requires-Dist: numpy
Requires-Dist: matplotlib
